firFilter/ADD.v


module ADD #
(
  parameter N = 16
)
(
  input CLK,
  input RST,
  input EN,
  input R_IN1,
  input [N-1:0] D_IN1,
  input R_IN2,
  input [N-1:0] D_IN2,
  output R_OUT,
  output [N-1:0] D_OUT
);

  reg [N-1:0] D_OUT_REG;
  reg R_OUT_REG;
  assign D_OUT = D_OUT_REG;
  assign R_OUT = R_OUT_REG;

  always @(posedge CLK) begin
    if(RST) begin
      R_OUT_REG <= 0;
      D_OUT_REG <= 0;
    end else begin
      if(CLK) begin
        if(EN) begin
          if(R_IN1 & R_IN2) begin
            D_OUT_REG <= D_IN1 + D_IN2;
            R_OUT_REG <= R_IN1;
          end else begin
            R_OUT_REG <= 0;
          end
        end 
      end 
    end
  end


endmodule

firFilter/muli.v
module MULI #
(
  parameter N = 16,
  parameter I = 1
)
(
  input CLK,
  input RST,
  input EN,
  input R_IN,
  input [N-1:0] D_IN,
  output R_OUT,
  output [N-1:0] D_OUT
);

  reg [N-1:0] D_OUT_REG;
  reg R_OUT_REG;
  assign D_OUT = D_OUT_REG;
  assign R_OUT = R_OUT_REG;

  always @(posedge CLK) begin
    if(RST) begin
      R_OUT_REG <= 0;
      D_OUT_REG <= 0;
    end else begin
      if(CLK) begin
        if(EN) begin
          if(R_IN) begin
            D_OUT_REG <= D_IN * I;
            R_OUT_REG <= R_IN;
          end else begin
            R_OUT_REG <= 0;
          end
        end 
      end 
    end
  end
endmodule

firFilter/REG.v


module REG #
(
  parameter N = 16,
  parameter I = 0
)
(
  input CLK,
  input RST,
  input EN,
  input R_IN,
  input [N-1:0] D_IN,
  output R_OUT,
  output [N-1:0] D_OUT
);

  reg [N-1:0] D_OUT_REG;
  reg R_OUT_REG;
  assign D_OUT = D_OUT_REG;
  assign R_OUT = R_OUT_REG;

  always @(posedge CLK) begin
    if(RST) begin
      R_OUT_REG <= 0;
    end else begin
      if(CLK) begin
        if(EN) begin
          if(R_IN) begin
            D_OUT_REG <= D_IN;
            R_OUT_REG <= R_IN;
          end else begin
            R_OUT_REG <= 0;
          end
        end 
      end 
    end
  end


endmodule

firFilter/firFilter.v
`include "add.v"
`include "muli.v"
`include "reg.v"

module firFilter(input enable,input clk, input rst, input [15:0] dataIn,input rin);
wire [1-1:0]en_wire;
wire [16-1:0]n9;
wire [1-1:0]n8;
wire [1-1:0]n7;
wire [16-1:0]n6;
wire [16-1:0]n5;
wire [1-1:0]n4;
wire [1-1:0]n3;
wire [16-1:0]n17;
wire [16-1:0]n2;
wire [1-1:0]n16;
wire [1-1:0]n1;
wire [1-1:0]n15;
wire [16-1:0]n0;
wire [16-1:0]n14;
wire [1-1:0]reset_wire;
wire [16-1:0]n13;
wire [1-1:0]n12;
wire [1-1:0]n11;
wire [16-1:0]n10;
wire [1-1:0]clock_wire;

assign clock_wire = clk;
assign en_wire = enable;
assign reset_wire = rst;
assign n14 = dataIn;
assign n16 = rin;

REG #(.N(16),.I(1.0E-8)) REG0(.CLK(clock_wire),.RST(reset_wire),.EN(en_wire),.R_IN(n1),.D_IN(n0),.R_OUT(n3),.D_OUT(n2));
MULI #(.N(16),.I(4)) MULI1(.CLK(clock_wire),.RST(reset_wire),.EN(en_wire),.R_IN(n16),.D_IN(n14),.R_OUT(n1),.D_OUT(n0));
MULI #(.N(16),.I(3)) MULI2(.CLK(clock_wire),.RST(reset_wire),.EN(en_wire),.R_IN(n16),.D_IN(n14),.R_OUT(n4),.D_OUT(n5));
MULI #(.N(16),.I(2)) MULI3(.CLK(clock_wire),.RST(reset_wire),.EN(en_wire),.R_IN(n16),.D_IN(n14),.R_OUT(n8),.D_OUT(n9));
MULI #(.N(16),.I(1)) MULI4(.CLK(clock_wire),.RST(reset_wire),.EN(en_wire),.R_IN(n16),.D_IN(n14),.R_OUT(n12),.D_OUT(n13));
ADD #(.N(16)) ADD0(.CLK(clock_wire),.RST(reset_wire),.EN(en_wire),.R_IN1(n11),.D_IN1(n10),.R_OUT(n15),.D_OUT(n17),.D_IN2(n13),.R_IN2(n12));
ADD #(.N(16)) ADD1(.CLK(clock_wire),.RST(reset_wire),.EN(en_wire),.R_IN1(n7),.D_IN1(n6),.R_OUT(n11),.D_OUT(n10),.D_IN2(n9),.R_IN2(n8));
ADD #(.N(16)) ADD2(.CLK(clock_wire),.RST(reset_wire),.EN(en_wire),.R_IN1(n3),.D_IN1(n2),.R_OUT(n7),.D_OUT(n6),.D_IN2(n5),.R_IN2(n4));
endmodule

firFilter/counter.v
module counter (clk,rst,enable,out,r_out);



input clk,rst,enable;

output reg [15:0] out;
output reg r_out;
always@(posedge clk) begin

if (rst) begin
 out <=0;
 r_out <= 1;
end else begin
  if (out == 10) begin
   r_out<=0;
   out <=0;
  end
  else begin
  if (enable) begin
    out <= out + 1;
    r_out <= 1;
  end
 end 
end
end





endmodule

firFilter/topFPGA.v

`include "firFilter.v"
`include "counter.v"


module topFPGA(

input clk,
input rst,
input en,
output LEDG,
output [6:0] HEX0,
output [6:0] HEX1
);
wire r_out;
wire newclk;
counter counter(.clk(clk),.rst(rst),.enable(en),.out(cont_in),.r_out(r_out));
wire [15:0] cont_in;
wire [15:0] data_out;
firFilter fir4_(
  .clk(clk),
  .rst(rst),
  .enable(en),
  .rin(r_out),
  .dataIn(cont_in)
 );

endmodule

firFilter/testbench.v
`include "topFPGA.v"

module tb();

reg clk;
reg rst;

topFPGA fpga1(.clk(clk),.rst(rst),.en(1'b1));


always
#1 clk = ~clk;


initial begin
clk =0;
rst =1;
#3 rst = 0;

end

initial begin
$dumpfile("out.vcd");
$dumpvars();
end


initial
#1000 $finish;


endmodule

firFilter/out.vcd
$date
	Wed May 17 16:37:24 2017
$end
$version
	Icarus Verilog
$end
$timescale
	1s
$end
$scope module tb $end
$var reg 1 ! clk $end
$var reg 1 " rst $end
$scope module fpga1 $end
$var wire 7 # HEX0 [6:0] $end
$var wire 7 $ HEX1 [6:0] $end
$var wire 1 % LEDG $end
$var wire 1 & clk $end
$var wire 16 ' cont_in [15:0] $end
$var wire 1 ( en $end
$var wire 1 ) r_out $end
$var wire 1 * rst $end
$scope module counter $end
$var wire 1 & clk $end
$var wire 1 ( enable $end
$var wire 1 * rst $end
$var reg 16 + out [15:0] $end
$var reg 1 , r_out $end
$upscope $end
$scope module fir4_ $end
$var wire 1 & clk $end
$var wire 1 - clock_wire $end
$var wire 16 . dataIn [15:0] $end
$var wire 1 / en_wire $end
$var wire 1 ( enable $end
$var wire 16 0 n0 [15:0] $end
$var wire 1 1 n1 $end
$var wire 16 2 n10 [15:0] $end
$var wire 1 3 n11 $end
$var wire 1 4 n12 $end
$var wire 16 5 n13 [15:0] $end
$var wire 16 6 n14 [15:0] $end
$var wire 1 7 n15 $end
$var wire 1 8 n16 $end
$var wire 16 9 n17 [15:0] $end
$var wire 16 : n2 [15:0] $end
$var wire 1 ; n3 $end
$var wire 1 < n4 $end
$var wire 16 = n5 [15:0] $end
$var wire 16 > n6 [15:0] $end
$var wire 1 ? n7 $end
$var wire 1 @ n8 $end
$var wire 16 A n9 [15:0] $end
$var wire 1 B reset_wire $end
$var wire 1 ) rin $end
$var wire 1 * rst $end
$scope module REG0 $end
$var wire 1 - CLK $end
$var wire 16 C D_IN [15:0] $end
$var wire 16 D D_OUT [15:0] $end
$var wire 1 / EN $end
$var wire 1 B RST $end
$var wire 1 1 R_IN $end
$var wire 1 ; R_OUT $end
$var reg 16 E D_OUT_REG [15:0] $end
$var reg 1 F R_OUT_REG $end
$upscope $end
$scope module MULI1 $end
$var wire 1 - CLK $end
$var wire 16 G D_IN [15:0] $end
$var wire 16 H D_OUT [15:0] $end
$var wire 1 / EN $end
$var wire 1 B RST $end
$var wire 1 8 R_IN $end
$var wire 1 1 R_OUT $end
$var reg 16 I D_OUT_REG [15:0] $end
$var reg 1 J R_OUT_REG $end
$upscope $end
$scope module MULI2 $end
$var wire 1 - CLK $end
$var wire 16 K D_IN [15:0] $end
$var wire 16 L D_OUT [15:0] $end
$var wire 1 / EN $end
$var wire 1 B RST $end
$var wire 1 8 R_IN $end
$var wire 1 < R_OUT $end
$var reg 16 M D_OUT_REG [15:0] $end
$var reg 1 N R_OUT_REG $end
$upscope $end
$scope module MULI3 $end
$var wire 1 - CLK $end
$var wire 16 O D_IN [15:0] $end
$var wire 16 P D_OUT [15:0] $end
$var wire 1 / EN $end
$var wire 1 B RST $end
$var wire 1 8 R_IN $end
$var wire 1 @ R_OUT $end
$var reg 16 Q D_OUT_REG [15:0] $end
$var reg 1 R R_OUT_REG $end
$upscope $end
$scope module MULI4 $end
$var wire 1 - CLK $end
$var wire 16 S D_IN [15:0] $end
$var wire 16 T D_OUT [15:0] $end
$var wire 1 / EN $end
$var wire 1 B RST $end
$var wire 1 8 R_IN $end
$var wire 1 4 R_OUT $end
$var reg 16 U D_OUT_REG [15:0] $end
$var reg 1 V R_OUT_REG $end
$upscope $end
$scope module ADD0 $end
$var wire 1 - CLK $end
$var wire 16 W D_IN1 [15:0] $end
$var wire 16 X D_IN2 [15:0] $end
$var wire 16 Y D_OUT [15:0] $end
$var wire 1 / EN $end
$var wire 1 B RST $end
$var wire 1 3 R_IN1 $end
$var wire 1 4 R_IN2 $end
$var wire 1 7 R_OUT $end
$var reg 16 Z D_OUT_REG [15:0] $end
$var reg 1 [ R_OUT_REG $end
$upscope $end
$scope module ADD1 $end
$var wire 1 - CLK $end
$var wire 16 \ D_IN1 [15:0] $end
$var wire 16 ] D_IN2 [15:0] $end
$var wire 16 ^ D_OUT [15:0] $end
$var wire 1 / EN $end
$var wire 1 B RST $end
$var wire 1 ? R_IN1 $end
$var wire 1 @ R_IN2 $end
$var wire 1 3 R_OUT $end
$var reg 16 _ D_OUT_REG [15:0] $end
$var reg 1 ` R_OUT_REG $end
$upscope $end
$scope module ADD2 $end
$var wire 1 - CLK $end
$var wire 16 a D_IN1 [15:0] $end
$var wire 16 b D_IN2 [15:0] $end
$var wire 16 c D_OUT [15:0] $end
$var wire 1 / EN $end
$var wire 1 B RST $end
$var wire 1 ; R_IN1 $end
$var wire 1 < R_IN2 $end
$var wire 1 ? R_OUT $end
$var reg 16 d D_OUT_REG [15:0] $end
$var reg 1 e R_OUT_REG $end
$upscope $end
$upscope $end
$upscope $end
$upscope $end
$enddefinitions $end
#0
$dumpvars
xe
bx d
bx c
bx b
bx a
x`
bx _
bx ^
bx ]
bx \
x[
bx Z
bx Y
bx X
bx W
xV
bx U
bx T
bx S
xR
bx Q
bx P
bx O
xN
bx M
bx L
bx K
xJ
bx I
bx H
bx G
xF
bx E
bx D
bx C
1B
bx A
x@
x?
bx >
bx =
x<
x;
bx :
bx 9
x8
x7
bx 6
bx 5
x4
x3
bx 2
x1
bx 0
1/
bx .
0-
x,
bx +
1*
x)
1(
bx '
0&
z%
bz $
bz #
1"
0!
$end
#1
1,
18
1)
b0 +
b0 6
b0 G
b0 K
b0 O
b0 S
b0 '
b0 .
0F
0;
b0 I
b0 0
b0 C
b0 H
0J
01
b0 M
b0 =
b0 L
b0 b
0N
0<
b0 Q
b0 A
b0 P
b0 ]
0R
0@
b0 U
b0 5
b0 T
b0 X
0V
04
b0 Z
b0 9
b0 Y
0[
07
b0 _
b0 2
b0 W
b0 ^
0`
03
b0 d
b0 >
b0 \
b0 c
0e
0?
1!
1&
1-
#2
0!
0&
0-
#3
b1 +
b1 6
b1 G
b1 K
b1 O
b1 S
b1 '
b1 .
1V
14
1R
1@
1N
1<
1J
11
1!
1&
1-
0"
0*
0B
#4
0!
0&
0-
#5
b10 +
b10 6
b10 G
b10 K
b10 O
b10 S
b10 '
b10 .
1F
1;
b0 E
b0 :
b0 D
b0 a
b100 I
b100 0
b100 C
b100 H
b11 M
b11 =
b11 L
b11 b
b10 Q
b10 A
b10 P
b10 ]
b1 U
b1 5
b1 T
b1 X
1!
1&
1-
#6
0!
0&
0-
#7
b11 +
b11 6
b11 G
b11 K
b11 O
b11 S
b11 '
b11 .
1e
1?
b11 d
b11 >
b11 \
b11 c
b10 U
b10 5
b10 T
b10 X
b100 Q
b100 A
b100 P
b100 ]
b110 M
b110 =
b110 L
b110 b
b1000 I
b1000 0
b1000 C
b1000 H
b100 E
b100 :
b100 D
b100 a
1!
1&
1-
#8
0!
0&
0-
#9
b100 +
b100 6
b100 G
b100 K
b100 O
b100 S
b100 '
b100 .
b1000 E
b1000 :
b1000 D
b1000 a
b1100 I
b1100 0
b1100 C
b1100 H
b1001 M
b1001 =
b1001 L
b1001 b
b110 Q
b110 A
b110 P
b110 ]
b11 U
b11 5
b11 T
b11 X
1`
13
b111 _
b111 2
b111 W
b111 ^
b1010 d
b1010 >
b1010 \
b1010 c
1!
1&
1-
#10
0!
0&
0-
#11
b101 +
b101 6
b101 G
b101 K
b101 O
b101 S
b101 '
b101 .
b10001 d
b10001 >
b10001 \
b10001 c
b10000 _
b10000 2
b10000 W
b10000 ^
1[
17
b1010 Z
b1010 9
b1010 Y
b100 U
b100 5
b100 T
b100 X
b1000 Q
b1000 A
b1000 P
b1000 ]
b1100 M
b1100 =
b1100 L
b1100 b
b10000 I
b10000 0
b10000 C
b10000 H
b1100 E
b1100 :
b1100 D
b1100 a
1!
1&
1-
#12
0!
0&
0-
#13
b110 +
b110 6
b110 G
b110 K
b110 O
b110 S
b110 '
b110 .
b10000 E
b10000 :
b10000 D
b10000 a
b10100 I
b10100 0
b10100 C
b10100 H
b1111 M
b1111 =
b1111 L
b1111 b
b1010 Q
b1010 A
b1010 P
b1010 ]
b101 U
b101 5
b101 T
b101 X
b10100 Z
b10100 9
b10100 Y
b11001 _
b11001 2
b11001 W
b11001 ^
b11000 d
b11000 >
b11000 \
b11000 c
1!
1&
1-
#14
0!
0&
0-
#15
b111 +
b111 6
b111 G
b111 K
b111 O
b111 S
b111 '
b111 .
b11111 d
b11111 >
b11111 \
b11111 c
b100010 _
b100010 2
b100010 W
b100010 ^
b11110 Z
b11110 9
b11110 Y
b110 U
b110 5
b110 T
b110 X
b1100 Q
b1100 A
b1100 P
b1100 ]
b10010 M
b10010 =
b10010 L
b10010 b
b11000 I
b11000 0
b11000 C
b11000 H
b10100 E
b10100 :
b10100 D
b10100 a
1!
1&
1-
#16
0!
0&
0-
#17
b1000 +
b1000 6
b1000 G
b1000 K
b1000 O
b1000 S
b1000 '
b1000 .
b11000 E
b11000 :
b11000 D
b11000 a
b11100 I
b11100 0
b11100 C
b11100 H
b10101 M
b10101 =
b10101 L
b10101 b
b1110 Q
b1110 A
b1110 P
b1110 ]
b111 U
b111 5
b111 T
b111 X
b101000 Z
b101000 9
b101000 Y
b101011 _
b101011 2
b101011 W
b101011 ^
b100110 d
b100110 >
b100110 \
b100110 c
1!
1&
1-
#18
0!
0&
0-
#19
b1001 +
b1001 6
b1001 G
b1001 K
b1001 O
b1001 S
b1001 '
b1001 .
b101101 d
b101101 >
b101101 \
b101101 c
b110100 _
b110100 2
b110100 W
b110100 ^
b110010 Z
b110010 9
b110010 Y
b1000 U
b1000 5
b1000 T
b1000 X
b10000 Q
b10000 A
b10000 P
b10000 ]
b11000 M
b11000 =
b11000 L
b11000 b
b100000 I
b100000 0
b100000 C
b100000 H
b11100 E
b11100 :
b11100 D
b11100 a
1!
1&
1-
#20
0!
0&
0-
#21
b1010 +
b1010 6
b1010 G
b1010 K
b1010 O
b1010 S
b1010 '
b1010 .
b100000 E
b100000 :
b100000 D
b100000 a
b100100 I
b100100 0
b100100 C
b100100 H
b11011 M
b11011 =
b11011 L
b11011 b
b10010 Q
b10010 A
b10010 P
b10010 ]
b1001 U
b1001 5
b1001 T
b1001 X
b111100 Z
b111100 9
b111100 Y
b111101 _
b111101 2
b111101 W
b111101 ^
b110100 d
b110100 >
b110100 \
b110100 c
1!
1&
1-
#22
0!
0&
0-
#23
b0 +
b0 6
b0 G
b0 K
b0 O
b0 S
b0 '
b0 .
0,
08
0)
b111011 d
b111011 >
b111011 \
b111011 c
b1000110 _
b1000110 2
b1000110 W
b1000110 ^
b1000110 Z
b1000110 9
b1000110 Y
b1010 U
b1010 5
b1010 T
b1010 X
b10100 Q
b10100 A
b10100 P
b10100 ]
b11110 M
b11110 =
b11110 L
b11110 b
b101000 I
b101000 0
b101000 C
b101000 H
b100100 E
b100100 :
b100100 D
b100100 a
1!
1&
1-
#24
0!
0&
0-
#25
1,
18
1)
b1 +
b1 6
b1 G
b1 K
b1 O
b1 S
b1 '
b1 .
b101000 E
b101000 :
b101000 D
b101000 a
0J
01
0N
0<
0R
0@
0V
04
b1010000 Z
b1010000 9
b1010000 Y
b1001111 _
b1001111 2
b1001111 W
b1001111 ^
b1000010 d
b1000010 >
b1000010 \
b1000010 c
1!
1&
1-
#26
0!
0&
0-
#27
b10 +
b10 6
b10 G
b10 K
b10 O
b10 S
b10 '
b10 .
0e
0?
0`
03
0[
07
1V
14
b1 U
b1 5
b1 T
b1 X
1R
1@
b10 Q
b10 A
b10 P
b10 ]
1N
1<
b11 M
b11 =
b11 L
b11 b
1J
11
b100 I
b100 0
b100 C
b100 H
0F
0;
1!
1&
1-
#28
0!
0&
0-
#29
b11 +
b11 6
b11 G
b11 K
b11 O
b11 S
b11 '
b11 .
1F
1;
b100 E
b100 :
b100 D
b100 a
b1000 I
b1000 0
b1000 C
b1000 H
b110 M
b110 =
b110 L
b110 b
b100 Q
b100 A
b100 P
b100 ]
b10 U
b10 5
b10 T
b10 X
1!
1&
1-
#30
0!
0&
0-
#31
b100 +
b100 6
b100 G
b100 K
b100 O
b100 S
b100 '
b100 .
1e
1?
b1010 d
b1010 >
b1010 \
b1010 c
b11 U
b11 5
b11 T
b11 X
b110 Q
b110 A
b110 P
b110 ]
b1001 M
b1001 =
b1001 L
b1001 b
b1100 I
b1100 0
b1100 C
b1100 H
b1000 E
b1000 :
b1000 D
b1000 a
1!
1&
1-
#32
0!
0&
0-
#33
b101 +
b101 6
b101 G
b101 K
b101 O
b101 S
b101 '
b101 .
b1100 E
b1100 :
b1100 D
b1100 a
b10000 I
b10000 0
b10000 C
b10000 H
b1100 M
b1100 =
b1100 L
b1100 b
b1000 Q
b1000 A
b1000 P
b1000 ]
b100 U
b100 5
b100 T
b100 X
1`
13
b10000 _
b10000 2
b10000 W
b10000 ^
b10001 d
b10001 >
b10001 \
b10001 c
1!
1&
1-
#34
0!
0&
0-
#35
b110 +
b110 6
b110 G
b110 K
b110 O
b110 S
b110 '
b110 .
b11000 d
b11000 >
b11000 \
b11000 c
b11001 _
b11001 2
b11001 W
b11001 ^
1[
17
b10100 Z
b10100 9
b10100 Y
b101 U
b101 5
b101 T
b101 X
b1010 Q
b1010 A
b1010 P
b1010 ]
b1111 M
b1111 =
b1111 L
b1111 b
b10100 I
b10100 0
b10100 C
b10100 H
b10000 E
b10000 :
b10000 D
b10000 a
1!
1&
1-
#36
0!
0&
0-
#37
b111 +
b111 6
b111 G
b111 K
b111 O
b111 S
b111 '
b111 .
b10100 E
b10100 :
b10100 D
b10100 a
b11000 I
b11000 0
b11000 C
b11000 H
b10010 M
b10010 =
b10010 L
b10010 b
b1100 Q
b1100 A
b1100 P
b1100 ]
b110 U
b110 5
b110 T
b110 X
b11110 Z
b11110 9
b11110 Y
b100010 _
b100010 2
b100010 W
b100010 ^
b11111 d
b11111 >
b11111 \
b11111 c
1!
1&
1-
#38
0!
0&
0-
#39
b1000 +
b1000 6
b1000 G
b1000 K
b1000 O
b1000 S
b1000 '
b1000 .
b100110 d
b100110 >
b100110 \
b100110 c
b101011 _
b101011 2
b101011 W
b101011 ^
b101000 Z
b101000 9
b101000 Y
b111 U
b111 5
b111 T
b111 X
b1110 Q
b1110 A
b1110 P
b1110 ]
b10101 M
b10101 =
b10101 L
b10101 b
b11100 I
b11100 0
b11100 C
b11100 H
b11000 E
b11000 :
b11000 D
b11000 a
1!
1&
1-
#40
0!
0&
0-
#41
b1001 +
b1001 6
b1001 G
b1001 K
b1001 O
b1001 S
b1001 '
b1001 .
b11100 E
b11100 :
b11100 D
b11100 a
b100000 I
b100000 0
b100000 C
b100000 H
b11000 M
b11000 =
b11000 L
b11000 b
b10000 Q
b10000 A
b10000 P
b10000 ]
b1000 U
b1000 5
b1000 T
b1000 X
b110010 Z
b110010 9
b110010 Y
b110100 _
b110100 2
b110100 W
b110100 ^
b101101 d
b101101 >
b101101 \
b101101 c
1!
1&
1-
#42
0!
0&
0-
#43
b1010 +
b1010 6
b1010 G
b1010 K
b1010 O
b1010 S
b1010 '
b1010 .
b110100 d
b110100 >
b110100 \
b110100 c
b111101 _
b111101 2
b111101 W
b111101 ^
b111100 Z
b111100 9
b111100 Y
b1001 U
b1001 5
b1001 T
b1001 X
b10010 Q
b10010 A
b10010 P
b10010 ]
b11011 M
b11011 =
b11011 L
b11011 b
b100100 I
b100100 0
b100100 C
b100100 H
b100000 E
b100000 :
b100000 D
b100000 a
1!
1&
1-
#44
0!
0&
0-
#45
b0 +
b0 6
b0 G
b0 K
b0 O
b0 S
b0 '
b0 .
0,
08
0)
b100100 E
b100100 :
b100100 D
b100100 a
b101000 I
b101000 0
b101000 C
b101000 H
b11110 M
b11110 =
b11110 L
b11110 b
b10100 Q
b10100 A
b10100 P
b10100 ]
b1010 U
b1010 5
b1010 T
b1010 X
b1000110 Z
b1000110 9
b1000110 Y
b1000110 _
b1000110 2
b1000110 W
b1000110 ^
b111011 d
b111011 >
b111011 \
b111011 c
1!
1&
1-
#46
0!
0&
0-
#47
1,
18
1)
b1 +
b1 6
b1 G
b1 K
b1 O
b1 S
b1 '
b1 .
b1000010 d
b1000010 >
b1000010 \
b1000010 c
b1001111 _
b1001111 2
b1001111 W
b1001111 ^
b1010000 Z
b1010000 9
b1010000 Y
0V
04
0R
0@
0N
0<
0J
01
b101000 E
b101000 :
b101000 D
b101000 a
1!
1&
1-
#48
0!
0&
0-
#49
b10 +
b10 6
b10 G
b10 K
b10 O
b10 S
b10 '
b10 .
0F
0;
1J
11
b100 I
b100 0
b100 C
b100 H
1N
1<
b11 M
b11 =
b11 L
b11 b
1R
1@
b10 Q
b10 A
b10 P
b10 ]
1V
14
b1 U
b1 5
b1 T
b1 X
0[
07
0`
03
0e
0?
1!
1&
1-
#50
0!
0&
0-
#51
b11 +
b11 6
b11 G
b11 K
b11 O
b11 S
b11 '
b11 .
b10 U
b10 5
b10 T
b10 X
b100 Q
b100 A
b100 P
b100 ]
b110 M
b110 =
b110 L
b110 b
b1000 I
b1000 0
b1000 C
b1000 H
1F
1;
b100 E
b100 :
b100 D
b100 a
1!
1&
1-
#52
0!
0&
0-
#53
b100 +
b100 6
b100 G
b100 K
b100 O
b100 S
b100 '
b100 .
b1000 E
b1000 :
b1000 D
b1000 a
b1100 I
b1100 0
b1100 C
b1100 H
b1001 M
b1001 =
b1001 L
b1001 b
b110 Q
b110 A
b110 P
b110 ]
b11 U
b11 5
b11 T
b11 X
1e
1?
b1010 d
b1010 >
b1010 \
b1010 c
1!
1&
1-
#54
0!
0&
0-
#55
b101 +
b101 6
b101 G
b101 K
b101 O
b101 S
b101 '
b101 .
b10001 d
b10001 >
b10001 \
b10001 c
1`
13
b10000 _
b10000 2
b10000 W
b10000 ^
b100 U
b100 5
b100 T
b100 X
b1000 Q
b1000 A
b1000 P
b1000 ]
b1100 M
b1100 =
b1100 L
b1100 b
b10000 I
b10000 0
b10000 C
b10000 H
b1100 E
b1100 :
b1100 D
b1100 a
1!
1&
1-
#56
0!
0&
0-
#57
b110 +
b110 6
b110 G
b110 K
b110 O
b110 S
b110 '
b110 .
b10000 E
b10000 :
b10000 D
b10000 a
b10100 I
b10100 0
b10100 C
b10100 H
b1111 M
b1111 =
b1111 L
b1111 b
b1010 Q
b1010 A
b1010 P
b1010 ]
b101 U
b101 5
b101 T
b101 X
1[
17
b10100 Z
b10100 9
b10100 Y
b11001 _
b11001 2
b11001 W
b11001 ^
b11000 d
b11000 >
b11000 \
b11000 c
1!
1&
1-
#58
0!
0&
0-
#59
b111 +
b111 6
b111 G
b111 K
b111 O
b111 S
b111 '
b111 .
b11111 d
b11111 >
b11111 \
b11111 c
b100010 _
b100010 2
b100010 W
b100010 ^
b11110 Z
b11110 9
b11110 Y
b110 U
b110 5
b110 T
b110 X
b1100 Q
b1100 A
b1100 P
b1100 ]
b10010 M
b10010 =
b10010 L
b10010 b
b11000 I
b11000 0
b11000 C
b11000 H
b10100 E
b10100 :
b10100 D
b10100 a
1!
1&
1-
#60
0!
0&
0-
#61
b1000 +
b1000 6
b1000 G
b1000 K
b1000 O
b1000 S
b1000 '
b1000 .
b11000 E
b11000 :
b11000 D
b11000 a
b11100 I
b11100 0
b11100 C
b11100 H
b10101 M
b10101 =
b10101 L
b10101 b
b1110 Q
b1110 A
b1110 P
b1110 ]
b111 U
b111 5
b111 T
b111 X
b101000 Z
b101000 9
b101000 Y
b101011 _
b101011 2
b101011 W
b101011 ^
b100110 d
b100110 >
b100110 \
b100110 c
1!
1&
1-
#62
0!
0&
0-
#63
b1001 +
b1001 6
b1001 G
b1001 K
b1001 O
b1001 S
b1001 '
b1001 .
b101101 d
b101101 >
b101101 \
b101101 c
b110100 _
b110100 2
b110100 W
b110100 ^
b110010 Z
b110010 9
b110010 Y
b1000 U
b1000 5
b1000 T
b1000 X
b10000 Q
b10000 A
b10000 P
b10000 ]
b11000 M
b11000 =
b11000 L
b11000 b
b100000 I
b100000 0
b100000 C
b100000 H
b11100 E
b11100 :
b11100 D
b11100 a
1!
1&
1-
#64
0!
0&
0-
#65
b1010 +
b1010 6
b1010 G
b1010 K
b1010 O
b1010 S
b1010 '
b1010 .
b100000 E
b100000 :
b100000 D
b100000 a
b100100 I
b100100 0
b100100 C
b100100 H
b11011 M
b11011 =
b11011 L
b11011 b
b10010 Q
b10010 A
b10010 P
b10010 ]
b1001 U
b1001 5
b1001 T
b1001 X
b111100 Z
b111100 9
b111100 Y
b111101 _
b111101 2
b111101 W
b111101 ^
b110100 d
b110100 >
b110100 \
b110100 c
1!
1&
1-
#66
0!
0&
0-
#67
b0 +
b0 6
b0 G
b0 K
b0 O
b0 S
b0 '
b0 .
0,
08
0)
b111011 d
b111011 >
b111011 \
b111011 c
b1000110 _
b1000110 2
b1000110 W
b1000110 ^
b1000110 Z
b1000110 9
b1000110 Y
b1010 U
b1010 5
b1010 T
b1010 X
b10100 Q
b10100 A
b10100 P
b10100 ]
b11110 M
b11110 =
b11110 L
b11110 b
b101000 I
b101000 0
b101000 C
b101000 H
b100100 E
b100100 :
b100100 D
b100100 a
1!
1&
1-
#68
0!
0&
0-
#69
1,
18
1)
b1 +
b1 6
b1 G
b1 K
b1 O
b1 S
b1 '
b1 .
b101000 E
b101000 :
b101000 D
b101000 a
0J
01
0N
0<
0R
0@
0V
04
b1010000 Z
b1010000 9
b1010000 Y
b1001111 _
b1001111 2
b1001111 W
b1001111 ^
b1000010 d
b1000010 >
b1000010 \
b1000010 c
1!
1&
1-
#70
0!
0&
0-
#71
b10 +
b10 6
b10 G
b10 K
b10 O
b10 S
b10 '
b10 .
0e
0?
0`
03
0[
07
1V
14
b1 U
b1 5
b1 T
b1 X
1R
1@
b10 Q
b10 A
b10 P
b10 ]
1N
1<
b11 M
b11 =
b11 L
b11 b
1J
11
b100 I
b100 0
b100 C
b100 H
0F
0;
1!
1&
1-
#72
0!
0&
0-
#73
b11 +
b11 6
b11 G
b11 K
b11 O
b11 S
b11 '
b11 .
1F
1;
b100 E
b100 :
b100 D
b100 a
b1000 I
b1000 0
b1000 C
b1000 H
b110 M
b110 =
b110 L
b110 b
b100 Q
b100 A
b100 P
b100 ]
b10 U
b10 5
b10 T
b10 X
1!
1&
1-
#74
0!
0&
0-
#75
b100 +
b100 6
b100 G
b100 K
b100 O
b100 S
b100 '
b100 .
1e
1?
b1010 d
b1010 >
b1010 \
b1010 c
b11 U
b11 5
b11 T
b11 X
b110 Q
b110 A
b110 P
b110 ]
b1001 M
b1001 =
b1001 L
b1001 b
b1100 I
b1100 0
b1100 C
b1100 H
b1000 E
b1000 :
b1000 D
b1000 a
1!
1&
1-
#76
0!
0&
0-
#77
b101 +
b101 6
b101 G
b101 K
b101 O
b101 S
b101 '
b101 .
b1100 E
b1100 :
b1100 D
b1100 a
b10000 I
b10000 0
b10000 C
b10000 H
b1100 M
b1100 =
b1100 L
b1100 b
b1000 Q
b1000 A
b1000 P
b1000 ]
b100 U
b100 5
b100 T
b100 X
1`
13
b10000 _
b10000 2
b10000 W
b10000 ^
b10001 d
b10001 >
b10001 \
b10001 c
1!
1&
1-
#78
0!
0&
0-
#79
b110 +
b110 6
b110 G
b110 K
b110 O
b110 S
b110 '
b110 .
b11000 d
b11000 >
b11000 \
b11000 c
b11001 _
b11001 2
b11001 W
b11001 ^
1[
17
b10100 Z
b10100 9
b10100 Y
b101 U
b101 5
b101 T
b101 X
b1010 Q
b1010 A
b1010 P
b1010 ]
b1111 M
b1111 =
b1111 L
b1111 b
b10100 I
b10100 0
b10100 C
b10100 H
b10000 E
b10000 :
b10000 D
b10000 a
1!
1&
1-
#80
0!
0&
0-
#81
b111 +
b111 6
b111 G
b111 K
b111 O
b111 S
b111 '
b111 .
b10100 E
b10100 :
b10100 D
b10100 a
b11000 I
b11000 0
b11000 C
b11000 H
b10010 M
b10010 =
b10010 L
b10010 b
b1100 Q
b1100 A
b1100 P
b1100 ]
b110 U
b110 5
b110 T
b110 X
b11110 Z
b11110 9
b11110 Y
b100010 _
b100010 2
b100010 W
b100010 ^
b11111 d
b11111 >
b11111 \
b11111 c
1!
1&
1-
#82
0!
0&
0-
